integrityguard/__init__.py
integrityguard/cli.py
integrityguard/hashreport.py
integrityguard/integrityguard.conf
integrityguard/integrityguard.py
integrityguard/monitor.py
integrityguard/data/__init__.py
integrityguard/data/hash.py
integrityguard/helpers/__init__.py
integrityguard/helpers/copyconfig.py
integrityguard/helpers/loadconfig.py
integrityguard/helpers/showpaths.py
integrityguard-0.4.3.dist-info/AUTHORS.rst
integrityguard-0.4.3.dist-info/LICENSE
integrityguard-0.4.3.dist-info/METADATA
integrityguard-0.4.3.dist-info/WHEEL
integrityguard-0.4.3.dist-info/entry_points.txt
integrityguard-0.4.3.dist-info/top_level.txt
integrityguard-0.4.3.dist-info/RECORD
