Metadata-Version: 2.1
Name: integrityguard
Version: 0.4.3
Summary: Multiplatform agent for file integrity monitoring. Monitors, generate logs, and notify.
Home-page: https://github.com/bruno-canada/integrityguard
Author: Bruno Bueno
Author-email: integrityguard@fastmail.com
License: MIT license
Keywords: integrityguard
Platform: UNKNOWN
Classifier: Development Status :: 3 - Alpha
Classifier: Intended Audience :: Developers
Classifier: License :: OSI Approved :: MIT License
Classifier: Natural Language :: English
Classifier: Programming Language :: Python :: 3
Classifier: Programming Language :: Python :: 3.6
Classifier: Programming Language :: Python :: 3.7
Classifier: Programming Language :: Python :: 3.8
Requires-Python: >=3.6
License-File: LICENSE
License-File: AUTHORS.rst
Requires-Dist: appdirs (>=1.4.4)
Requires-Dist: watchdog (>=1.0.2)
Requires-Dist: colorama (>=0.4.4)
Requires-Dist: click (==8.0.3)
